simple_graphql_client/__init__.py
simple_graphql_client/client.py
simple_graphql_client/helpers.py
simple_graphql_client-0.0.4.dist-info/LICENSE
simple_graphql_client-0.0.4.dist-info/METADATA
simple_graphql_client-0.0.4.dist-info/WHEEL
simple_graphql_client-0.0.4.dist-info/top_level.txt
simple_graphql_client-0.0.4.dist-info/RECORD
