Metadata-Version: 2.1
Name: simple-graphql-client
Version: 0.0.4
Summary: A simple graphql client which also supports file upload
Home-page: https://github.com/ams-pro/simple-graphql-client
Author: Fabian Riewe
Author-email: f.riewe@ams-pro.de
License: UNKNOWN
Platform: UNKNOWN
Classifier: Programming Language :: Python :: 3
Classifier: License :: OSI Approved :: MIT License
Classifier: Operating System :: OS Independent
Requires-Python: >=3.6
Requires-Dist: requests (==2.22.0)
Requires-Dist: graphql-server-core (==1.2.0)
